torchspider/__init__.py
torchspider/callbacks.py
torchspider/data.py
torchspider/learner.py
torchspider/torch_tools.py
torchspider/utils.py
torchspider-0.0.12.dist-info/LICENSE
torchspider-0.0.12.dist-info/METADATA
torchspider-0.0.12.dist-info/WHEEL
torchspider-0.0.12.dist-info/top_level.txt
torchspider-0.0.12.dist-info/RECORD
